{"supplychain":{"category":27,"created":1354736373,"enable_comments":true,"flags":0,"id":4778,"modified":1354737293,"other_perms":1,"passcode":null,"user_featured":false,"usergroup_id":null,"usergroup_perms":0,"user_id":4314,"owner":{"id":4314,"name":"sourcemap12","avatar":"http:\/\/free.sourcemap.com\/assets\/images\/default-user.png","banner_url":null,"display_name":null},"taxonomy":[{"description":"Automotive & Industrial","id":13,"left":21,"name":"industrial","right":24,"title":"Automotive & Industrial"},{"description":"Tools","id":27,"left":22,"name":"tools","right":23,"title":"Tools"}],"attributes":{"title":"Supply Chain India","description":"Ponta Negra","tags":"new"},"stops":[{"local_stop_id":4,"id":4,"geometry":"POINT(-4810069.2104261 -2620357.5079608)","attributes":{"supplychain_instance_id":"supplychain-1","stop_instance_id":"stop-57","description":"","address":"Rio de Janeiro, Brazil","title":"Rio de Janeiro"}},{"local_stop_id":3,"id":3,"geometry":"POINT(1619920.5284886 6800774.0411741)","attributes":{"supplychain_instance_id":"supplychain-1","stop_instance_id":"stop-18","description":"","address":"Lieberoser Stra\u00dfe 3, 03172 Schenkend\u00f6bern, Germany","title":"Europe"}},{"local_stop_id":1,"id":1,"geometry":"POINT(8112703.5438661 2163883.8099375)","attributes":{"youtube:link":"","water":"0","energy":"0","co2e":"0","weight":"0","supplychain_instance_id":"supplychain-1","stop_instance_id":"stop-1","description":"","address":"Mumbai, Maharashtra, India","title":"Mumbai "}}],"hops":[{"from_stop_id":1,"to_stop_id":3,"geometry":"MULTILINESTRING((8112703.5438661 2163883.8099375,1619920.5284885 6800774.0411741))","attributes":{"distance":"6221.810988","title":"Mumbai  to Europe","co2e":"0"}},{"from_stop_id":4,"to_stop_id":3,"geometry":"MULTILINESTRING((-4810069.2104261 -2620357.5079608,1619920.5284885 6800774.0411741))","attributes":{"distance":"10245.503782","title":"Rio de Janeiro to Europe","co2e":"0"}}]},"editable":false}