{"supplychain":{"category":19,"created":1313863460,"enable_comments":true,"flags":0,"id":485,"modified":1314216463,"other_perms":1,"passcode":null,"user_featured":false,"usergroup_id":null,"usergroup_perms":0,"user_id":5,"owner":{"id":5,"name":"sourcemap_archive","avatar":"http:\/\/free.sourcemap.com\/assets\/images\/default-user.png","banner_url":null,"display_name":null},"taxonomy":[{"description":"Test Maps","id":19,"left":35,"name":"test-maps","right":36,"title":"Test Maps "}],"attributes":{"alias:preferred":"test-","description":"Created on June 21, 2011 by naoki on Sourcemap.org.","distance:transport":"6352.54","emissions:embodied":"0","emissions:total":"0","emissions:transport":"0","legacy:creator":"13610","legacy:distance":"6352.54","legacy:emissions":"0","legacy:oid":"1362","sm:migrated:time":"1313857773","title":"test ","weight":"0","tags":""},"stops":[{"local_stop_id":16469,"id":16469,"geometry":"POINT(2131226.790688 6785571.898792)","attributes":{"name":"test ","1":"Pologne","address":"Pologne","category":"1","title":"test ","qty":"0","co2e":"0","weight":"0","unit":"kg"}},{"local_stop_id":16470,"id":16470,"geometry":"POINT(11724030.288901 8747149.04879)","attributes":{"name":"Ambre","1":"Russie","address":"Russie","title":"Ambre","qty":"0","co2e":"0","weight":"0","unit":"kg"}},{"local_stop_id":16471,"id":16471,"geometry":"POINT(2131226.790688 6785571.898792)","attributes":{"name":"Argent","1":"Pologne","address":"Pologne","title":"Argent","qty":"0","co2e":"0","weight":"0","unit":"kg"}},{"local_stop_id":16472,"id":16472,"geometry":"POINT(2131226.790688 6785571.898792)","attributes":{"name":"Assemblage en Pologne","1":"Pologne","address":"Pologne","title":"Assemblage en Pologne","qty":"0","co2e":"0","weight":"0","unit":"kg"}},{"local_stop_id":16473,"id":16473,"geometry":"POINT(246433.411424 5816903.713427)","attributes":{"name":"Vente","1":"France","address":"France","title":"Vente","qty":"0","co2e":"0","weight":"0","unit":"kg"}}],"hops":[{"from_stop_id":16470,"to_stop_id":16469,"geometry":"MULTILINESTRING((11724030.288901 8747149.04879,2131226.790688 6785571.898792))","attributes":{"weight":"0","qty":"1","co2e":null}},{"from_stop_id":16471,"to_stop_id":16469,"geometry":"MULTILINESTRING((2131226.790688 6785571.898792,2131226.790688 6785571.898792))","attributes":{"weight":"0","qty":"1","co2e":null}},{"from_stop_id":16472,"to_stop_id":16469,"geometry":"MULTILINESTRING((2131226.790688 6785571.898792,2131226.790688 6785571.898792))","attributes":{"weight":"0","qty":"1","co2e":null}},{"from_stop_id":16473,"to_stop_id":16469,"geometry":"MULTILINESTRING((246433.411424 5816903.713427,2131226.790688 6785571.898792))","attributes":{"weight":"0","qty":"1","co2e":null}}]},"editable":false}