{"supplychain":{"category":47,"created":1365183652,"enable_comments":true,"flags":0,"id":5644,"modified":1365184246,"other_perms":1,"passcode":null,"user_featured":false,"usergroup_id":null,"usergroup_perms":0,"user_id":5257,"owner":{"id":5257,"name":"alexisarmani","avatar":"http:\/\/free.sourcemap.com\/assets\/images\/default-user.png","banner_url":null,"display_name":null},"taxonomy":[{"description":"food","id":47,"left":39,"name":"food","right":40,"title":"Food"}],"attributes":{"title":"Starbucks","description":"mocca cookie crumble","tags":"coffee"},"stops":[{"local_stop_id":1,"id":1,"geometry":"POINT(-11512027.916453 2939292.142932)","attributes":{"youtube:link":"http:\/\/www.youtube.com\/watch?v=_XNuvswcbgg","water":"0","energy":"0","co2e":"0","weight":"0","supplychain_instance_id":"supplychain-1","stop_instance_id":"stop-1","description":"the warehouse contain coffee ","address":"Apartado 1085, Campestre La Rosita, 27250 Torreon, Coahuila, Mexico","title":"Costa Rica "}}],"hops":[]},"editable":false}